flask_sqlalchemy_querylog/__init__.py
Flask_Sqlalchemy_QueryLog-0.0.0.dist-info/LICENSE
Flask_Sqlalchemy_QueryLog-0.0.0.dist-info/METADATA
Flask_Sqlalchemy_QueryLog-0.0.0.dist-info/WHEEL
Flask_Sqlalchemy_QueryLog-0.0.0.dist-info/top_level.txt
Flask_Sqlalchemy_QueryLog-0.0.0.dist-info/RECORD
